gfort2py/__init__.py
gfort2py/fArrays.py
gfort2py/fCompile.py
gfort2py/fDT.py
gfort2py/fParameters.py
gfort2py/fProc.py
gfort2py/fProcPtr.py
gfort2py/fScalars.py
gfort2py/fStrings.py
gfort2py/fUnary.py
gfort2py/fVar.py
gfort2py/fVar_t.py
gfort2py/gfort2py.py
gfort2py/module_parse.py
gfort2py/utils.py
gfort2py/version.py
gfort2py-2.6.2.dist-info/licenses/COPYING.txt
gfort2py-2.6.2.dist-info/METADATA
gfort2py-2.6.2.dist-info/WHEEL
gfort2py-2.6.2.dist-info/top_level.txt
gfort2py-2.6.2.dist-info/RECORD
