Metadata-Version: 2.4
Name: gfort2py
Version: 2.6.2
Summary: Python bindings for Fortran
Author-email: Robert Farmer <robert.j.farmer37@gmail.com>
License: GPLv2+
Classifier: Programming Language :: Python :: 3
Classifier: Programming Language :: Python :: 3 :: Only
Classifier: Programming Language :: Python :: 3.7
Classifier: Programming Language :: Python :: 3.8
Classifier: Programming Language :: Python :: 3.9
Classifier: Programming Language :: Python :: 3.10
Classifier: Programming Language :: Python :: 3.11
Classifier: Programming Language :: Python :: 3.12
Classifier: Topic :: Software Development :: Code Generators
Requires-Python: >=3.7
License-File: COPYING.txt
Requires-Dist: numpy<2.3,>=1.13.0
Requires-Dist: cpyparsing<=2.5,>=2.4.7
Requires-Dist: platformdirs<=5,>=3
Requires-Dist: dataclasses_json<=1.0,>=0.6
Requires-Dist: importlib_metadata
Provides-Extra: test
Requires-Dist: pytest; extra == "test"
Provides-Extra: quad
Requires-Dist: pyquadp; extra == "quad"
Provides-Extra: dev
Requires-Dist: pre-commit; extra == "dev"
Requires-Dist: black; extra == "dev"
Dynamic: license-file
